papermc_updater/__init__.py
papermc_updater/update_paper.py
papermc_updater-0.1.3.dist-info/LICENSE
papermc_updater-0.1.3.dist-info/METADATA
papermc_updater-0.1.3.dist-info/WHEEL
papermc_updater-0.1.3.dist-info/entry_points.txt
papermc_updater-0.1.3.dist-info/top_level.txt
papermc_updater-0.1.3.dist-info/RECORD
